fuller/__init__.py
fuller/generator.py
fuller/metrics.py
fuller/mrfRec.py
fuller/reconstruction_mrf2d.py
fuller/utils.py
fuller-2.0.0.dist-info/licenses/LICENSE
fuller-2.0.0.dist-info/METADATA
fuller-2.0.0.dist-info/WHEEL
fuller-2.0.0.dist-info/top_level.txt
fuller-2.0.0.dist-info/RECORD
