Metadata-Version: 2.4
Name: fuller
Version: 2.0.0
Summary: Integrated computational framework for electronic band structure reconstruction and parametrization
Author: Vincent Stimper, R. Patrick Xian
Project-URL: Homepage, https://github.com/mpes-kit/fuller
Classifier: Development Status :: 3 - Alpha
Classifier: Intended Audience :: Developers
Classifier: Programming Language :: Python :: 3
Requires-Python: >=3.8
License-File: LICENSE
Requires-Dist: numpy<2
Requires-Dist: scipy
Requires-Dist: matplotlib
Requires-Dist: poppy
Requires-Dist: natsort
Requires-Dist: symmetrize
Requires-Dist: tqdm
Requires-Dist: silx
Requires-Dist: tensorflow>=2
Requires-Dist: protobuf
Provides-Extra: dev
Requires-Dist: ruff>=0.1.7; extra == "dev"
Requires-Dist: mypy>=1.6.0; extra == "dev"
Requires-Dist: pre-commit>=3.0.0; extra == "dev"
Provides-Extra: cuda
Requires-Dist: tensorflow[and-cuda]>=2; extra == "cuda"
Provides-Extra: examples
Requires-Dist: mpes; extra == "examples"
Requires-Dist: ipywidgets; extra == "examples"
Dynamic: license-file
